README.rst
setup.cfg
setup.py
pynet/__init__.py
pynet/cam.py
pynet/configure.py
pynet/core.py
pynet/history.py
pynet/info.py
pynet/interfaces.py
pynet/metrics.py
pynet/observable.py
pynet/utils.py
pynet/augmentation/__init__.py
pynet/augmentation/intensity.py
pynet/augmentation/spatial.py
pynet/augmentation/transform.py
pynet/augmentation/utils.py
pynet/datasets/__init__.py
pynet/datasets/biomede.py
pynet/datasets/brats.py
pynet/datasets/cifar.py
pynet/datasets/connectome.py
pynet/datasets/core.py
pynet/datasets/dsprites.py
pynet/datasets/echocardiography.py
pynet/datasets/euaims.py
pynet/datasets/genomic.py
pynet/datasets/gradcam.py
pynet/datasets/hbn.py
pynet/datasets/hcp.py
pynet/datasets/impac.py
pynet/datasets/lpsnc.py
pynet/datasets/metastasis.py
pynet/datasets/minst.py
pynet/datasets/orientation.py
pynet/datasets/primede.py
pynet/datasets/registration.py
pynet/datasets/tcga_lgg_tif.py
pynet/datasets/toy.py
pynet/datasets/ukb.py
pynet/losses/__init__.py
pynet/losses/common.py
pynet/losses/generative.py
pynet/losses/segmentation.py
pynet/models/__init__.py
pynet/models/attention.py
pynet/models/braingengan.py
pynet/models/brainnetcnn.py
pynet/models/cam.py
pynet/models/deepcluster.py
pynet/models/deeplabnet.py
pynet/models/nvnet.py
pynet/models/pspnet.py
pynet/models/rcnet.py
pynet/models/resnet.py
pynet/models/sononet.py
pynet/models/torchvisnet.py
pynet/models/unet.py
pynet/models/voxelmorphnet.py
pynet/models/vtnet.py
pynet/models/spherical/__init__.py
pynet/models/spherical/layers.py
pynet/models/spherical/sampling.py
pynet/models/spherical/unet.py
pynet/models/spherical/utils.py
pynet/models/vae/__init__.py
pynet/models/vae/distributions.py
pynet/models/vae/gmvae.py
pynet/models/vae/mcvae.py
pynet/models/vae/utils.py
pynet/models/vae/vade.py
pynet/models/vae/vae.py
pynet/plotting/__init__.py
pynet/plotting/board.py
pynet/plotting/colors.py
pynet/plotting/graph.py
pynet/plotting/image.py
pynet/plotting/network.py
pynet/plotting/signal.py
python_network.egg-info/PKG-INFO
python_network.egg-info/SOURCES.txt
python_network.egg-info/dependency_links.txt
python_network.egg-info/requires.txt
python_network.egg-info/top_level.txt