Metadata-Version: 1.1
Name: python-network
Version: 0.0.1
Summary: 
